setup.py
pylsdj/__init__.py
pylsdj/blockutils.py
pylsdj/bread_spec.py
pylsdj/chain.py
pylsdj/clock.py
pylsdj/consts.py
pylsdj/exceptions.py
pylsdj/filepack.py
pylsdj/instrument.py
pylsdj/instrument_mixins.py
pylsdj/instruments.py
pylsdj/kit_instrument.py
pylsdj/noise_instrument.py
pylsdj/phrase.py
pylsdj/project.py
pylsdj/pulse_instrument.py
pylsdj/savfile.py
pylsdj/song.py
pylsdj/speech_instrument.py
pylsdj/synth.py
pylsdj/table.py
pylsdj/test_blockutils.py
pylsdj/test_clock.py
pylsdj/test_filepack.py
pylsdj/test_instrument.py
pylsdj/test_phrase.py
pylsdj/test_project.py
pylsdj/test_savfile.py
pylsdj/test_synth.py
pylsdj/utils.py
pylsdj/vibrato.py
pylsdj/wave_instrument.py
pylsdj.egg-info/PKG-INFO
pylsdj.egg-info/SOURCES.txt
pylsdj.egg-info/dependency_links.txt
pylsdj.egg-info/not-zip-safe
pylsdj.egg-info/pbr.json
pylsdj.egg-info/requires.txt
pylsdj.egg-info/top_level.txt
pylsdj/vendor/__init__.py
pylsdj/vendor/six.py