Metadata-Version: 1.1
Name: pylsdj
Version: 2.3.2
Summary: A utility belt for dealing with LSDJ-related files
Home-page: http://github.com/alexras/pylsdj
Author: Alex Rasmussen
Author-email: alexras@acm.org
License: MIT
Platform: UNKNOWN
Classifier: Development Status :: 4 - Beta
Classifier: Environment :: Other Environment
Classifier: Intended Audience :: Developers
Classifier: License :: OSI Approved :: MIT License
Classifier: Natural Language :: English
Classifier: Operating System :: OS Independent
Classifier: Programming Language :: Python
Classifier: Programming Language :: Python :: 2.7
Classifier: Programming Language :: Python :: 3
Classifier: Topic :: Software Development :: Libraries :: Python Modules
Requires: bread
